src/__init__.py
src/server.py
src/common/__init__.py
src/common/constants.py
src/common/decorators.py
src/common/descriptors.py
src/common/errors.py
src/common/metaclasses.py
src/common/utils.py
src/docs/__init__.py
src/docs/source/__init__.py
src/docs/source/conf.py
src/logs/__init__.py
src/logs/client_log_config.py
src/logs/server/__init__.py
src/logs/server/server_log_config.py
src/server/__init__.py
src/server/add_user.py
src/server/core.py
src/server/del_user.py
src/server/server_db.py
src/server/server_gui.py
src/tests/__init__.py
sher_server_chat-0.0.1.dist-info/METADATA
sher_server_chat-0.0.1.dist-info/WHEEL
sher_server_chat-0.0.1.dist-info/top_level.txt
sher_server_chat-0.0.1.dist-info/RECORD
