Metadata-Version: 2.1
Name: sher-server-chat
Version: 0.0.1
Summary: sher_server_chat
Author: Yuriy Shereshkov
Author-email: yuriy.shereshkoff@gmail.com
Requires-Dist: PyQt5
Requires-Dist: sqlalchemy
